configorm/__init__.py
configorm/config_orm.py
configorm/connectors.py
configorm/fields.py
ConfigORM-1.0.1.dist-info/LICENSE
ConfigORM-1.0.1.dist-info/METADATA
ConfigORM-1.0.1.dist-info/WHEEL
ConfigORM-1.0.1.dist-info/top_level.txt
ConfigORM-1.0.1.dist-info/RECORD
