Metadata-Version: 2.1
Name: ConfigORM
Version: 1.0.1
Summary: ORM-like *.ini file and HashiCorp Vault config parser
Home-page: https://github.com/YADRO-KNS/ConfigORM
Author: Sergey Parshin
Author-email: parshinsp@gmail.com
Classifier: Development Status :: 5 - Production/Stable
Classifier: Programming Language :: Python :: 3.7
Classifier: Programming Language :: Python :: 3.8
Classifier: Programming Language :: Python :: 3.9
Classifier: Programming Language :: Python :: 3.10
Classifier: Programming Language :: Python :: 3.11
Classifier: License :: OSI Approved :: MIT License
Classifier: Operating System :: OS Independent
Requires-Python: >=3.7
License-File: LICENSE
Requires-Dist: hvac (>=1.0.2)
